evedesign/__about__.py
evedesign/__init__.py
evedesign-0.0.1.dist-info/METADATA
evedesign-0.0.1.dist-info/WHEEL
evedesign-0.0.1.dist-info/licenses/LICENSE.txt
evedesign-0.0.1.dist-info/RECORD
