Metadata-Version: 2.4
Name: evedesign
Version: 0.0.1
Project-URL: Documentation, https://github.com/Thomas Hopf/evedesign#readme
Project-URL: Issues, https://github.com/Thomas Hopf/evedesign/issues
Project-URL: Source, https://github.com/Thomas Hopf/evedesign
Author-email: Thomas Hopf <thomas.hopf@gmail.com>
License-Expression: MIT
License-File: LICENSE.txt
Classifier: Development Status :: 4 - Beta
Classifier: Programming Language :: Python
Classifier: Programming Language :: Python :: 3.8
Classifier: Programming Language :: Python :: 3.9
Classifier: Programming Language :: Python :: 3.10
Classifier: Programming Language :: Python :: 3.11
Classifier: Programming Language :: Python :: 3.12
Classifier: Programming Language :: Python :: Implementation :: CPython
Classifier: Programming Language :: Python :: Implementation :: PyPy
Requires-Python: >=3.8
